aussiebb/__init__.py
aussiebb/asyncio/__init__.py
aussiebb/baseclass.py
aussiebb/const.py
aussiebb/exceptions.py
aussiebb/py.typed
aussiebb/types.py
aussiebb/utils.py
pyaussiebb-0.1.6.dist-info/METADATA
pyaussiebb-0.1.6.dist-info/WHEEL
pyaussiebb-0.1.6.dist-info/entry_points.txt
pyaussiebb-0.1.6.dist-info/licenses/LICENSE
pyaussiebb-0.1.6.dist-info/RECORD
