Metadata-Version: 2.1
Name: pyaussiebb
Version: 0.1.6
Summary: Aussie Broadband API module
Keywords: api,aussie,broadband,internet
Author-Email: James Hodgkinson <james@terminaloutcomes.com>
License: MIT
Classifier: Development Status :: 4 - Beta
Classifier: Programming Language :: Python :: 3
Classifier: Programming Language :: Python :: 3.9
Classifier: Programming Language :: Python :: 3.10
Classifier: Programming Language :: Python :: 3.11
Classifier: Programming Language :: Python :: 3.12
Classifier: Programming Language :: Python :: 3.13
Classifier: License :: OSI Approved :: MIT License
Classifier: Operating System :: OS Independent
Project-URL: issues, https://github.com/yaleman/pyaussiebb/issues/
Project-URL: homepage, https://github.com/yaleman/pyaussiebb
Project-URL: repository, https://github.com/yaleman/pyaussiebb
Project-URL: documentation, https://yaleman.github.io/pyaussiebb/
Requires-Python: >=3.9
Requires-Dist: requests>=2.27.1
Requires-Dist: aiohttp>=3.11.18
Requires-Dist: pydantic>=2.11.4
